Metadata-Version: 1.0
Name: fancypipes
Version: 0.1.dev0
Summary: Making scikit-learn pipelines even more useful
Home-page: https://github.com/ieaves/better-pipelines
Author: Ian Eaves
Author-email: ian.k.eaves@gmail.com
License: MIT
Platform: UNKNOWN
